README.rst
ansiescapes.py
setup.py
ansiescapes.egg-info/PKG-INFO
ansiescapes.egg-info/SOURCES.txt
ansiescapes.egg-info/dependency_links.txt
ansiescapes.egg-info/top_level.txt