Metadata-Version: 1.1
Name: ansiescapes
Version: 1.0.0
Summary: ANSI escape codes for manipulating the terminal - A Python port of sindresorhus's ansi-escapes Node.js module
Home-page: https://github.com/kodie/ansiescapes
Author: Kodie Grantham
Author-email: kodie.grantham@gmail.com
License: MIT
Keywords: ansi terminal console cli string tty escape escapes formatting shell xterm log logging command-line text vt100 sequence control code codes cursor iterm iterm2
Platform: UNKNOWN
Classifier: Development Status :: 5 - Production/Stable
Classifier: Intended Audience :: Developers
Classifier: Topic :: Software Development :: Build Tools
Classifier: License :: OSI Approved :: MIT License
Classifier: Programming Language :: Python :: 2
Classifier: Programming Language :: Python :: 2.7
Classifier: Programming Language :: Python :: 3
Classifier: Programming Language :: Python :: 3.3
Classifier: Programming Language :: Python :: 3.4
Classifier: Programming Language :: Python :: 3.5
